[{"PlayerName":"Josh Allen","PlayerId":"2560955","Pos":"QB","Team":"BUF","PassingYDS":"4407","PassingTD":"36","PassingInt":"15","RushingYDS":"763","RushingTD":"6","ReceivingRec":"","ReceivingYDS":"","ReceivingTD":"","RetTD":"","FumTD":"","2PT":"3","Fum":"8","FanPtsAgainst-pts":"18.22","TouchCarries":"122","TouchReceptions":"","Touches":"122","TargetsReceptions":"","Targets":"","ReceptionPercentage":"","RzTarget":"","RzTouch":"32","RzG2G":"12","Rank":1,"TotalPoints":"397.85"},{"PlayerName":"Justin Herbert","PlayerId":"2565045","Pos":"QB","Team":"LAC","PassingYDS":"5014","PassingTD":"38","PassingInt":"15","RushingYDS":"302","RushingTD":"3","ReceivingRec":"","ReceivingYDS":"","ReceivingTD":"","RetTD":"","FumTD":"","2PT":"6","Fum":"1","FanPtsAgainst-pts":"16.24","TouchCarries":"63","TouchReceptions":"","Touches":"63","TargetsReceptions":"","Targets":"","ReceptionPercentage":"","RzTarget":"","RzTouch":"23","RzG2G":"11","Rank":2,"TotalPoints":"382.46"},{"PlayerName":"Tom Brady","PlayerId":"2504211","Pos":"QB","Team":"TB","PassingYDS":"5316","PassingTD":"43","PassingInt":"12","RushingYDS":"81","RushingTD":"2","ReceivingRec":"","ReceivingYDS":"","ReceivingTD":"","RetTD":"","FumTD":"","2PT":"","Fum":"4","FanPtsAgainst-pts":"15.29","TouchCarries":"28","TouchReceptions":"","Touches":"28","TargetsReceptions":"","Targets":"","ReceptionPercentage":"","RzTarget":"","RzTouch":"8","RzG2G":"5","Rank":3,"TotalPoints":"373.74"},{"PlayerName":"Patrick Mahomes","PlayerId":"2558125","Pos":"QB","Team":"KC","PassingYDS":"4839","PassingTD":"37","PassingInt":"13","RushingYDS":"381","RushingTD":"2","ReceivingRec":"","ReceivingYDS":"","ReceivingTD":"","RetTD":"","FumTD":"","2PT":"2","Fum":"9","FanPtsAgainst-pts":"14.22","TouchCarries":"66","TouchReceptions":"","Touches":"66","TargetsReceptions":"","Targets":"","ReceptionPercentage":"","RzTarget":"","RzTouch":"17","RzG2G":"8","Rank":4,"TotalPoints":"355.13"},{"PlayerName":"Aaron Rodgers","PlayerId":"2506363","Pos":"QB","Team":"GB","PassingYDS":"4115","PassingTD":"37","PassingInt":"4","RushingYDS":"101","RushingTD":"3","ReceivingRec":"1","ReceivingYDS":"-4","ReceivingTD":"","RetTD":"","FumTD":"","2PT":"","Fum":"3","FanPtsAgainst-pts":"17.47","TouchCarries":"33","TouchReceptions":"1","Touches":"34","TargetsReceptions":"1","Targets":"1","ReceptionPercentage":"100","RzTarget":"1","RzTouch":"8","RzG2G":"4","Rank":5,"TotalPoints":"328.67"},{"PlayerName":"Matthew Stafford","PlayerId":"79860","Pos":"QB","Team":"LA","PassingYDS":"4886","PassingTD":"41","PassingInt":"17","RushingYDS":"43","RushingTD":"","ReceivingRec":"","ReceivingYDS":"","ReceivingTD":"","RetTD":"","FumTD":"","2PT":"2","Fum":"5","FanPtsAgainst-pts":"16.38","TouchCarries":"32","TouchReceptions":"","Touches":"32","TargetsReceptions":"","Targets":"","ReceptionPercentage":"","RzTarget":"","RzTouch":"7","RzG2G":"3","Rank":6,"TotalPoints":"326.74"},{"PlayerName":"Dak Prescott","PlayerId":"2555260","Pos":"QB","Team":"DAL","PassingYDS":"4449","PassingTD":"37","PassingInt":"10","RushingYDS":"146","RushingTD":"1","ReceivingRec":"","ReceivingYDS":"","ReceivingTD":"","RetTD":"","FumTD":"","2PT":"3","Fum":"14","FanPtsAgainst-pts":"15.27","TouchCarries":"48","TouchReceptions":"","Touches":"48","TargetsReceptions":"","Targets":"","ReceptionPercentage":"","RzTarget":"","RzTouch":"15","RzG2G":"7","Rank":7,"TotalPoints":"312.86"},{"PlayerName":"Joe Burrow","PlayerId":"2563722","Pos":"QB","Team":"CIN","PassingYDS":"4611","PassingTD":"34","PassingInt":"14","RushingYDS":"118","RushingTD":"2","ReceivingRec":"","ReceivingYDS":"","ReceivingTD":"","RetTD":"","FumTD":"","2PT":"1","Fum":"5","FanPtsAgainst-pts":"15.86","TouchCarries":"40","TouchReceptions":"","Touches":"40","TargetsReceptions":"","Targets":"","ReceptionPercentage":"","RzTarget":"","RzTouch":"9","RzG2G":"5","Rank":8,"TotalPoints":"312.51"},{"PlayerName":"Jalen Hurts","PlayerId":"2564832","Pos":"QB","Team":"PHI","PassingYDS":"3144","PassingTD":"16","PassingInt":"9","RushingYDS":"784","RushingTD":"10","ReceivingRec":"","ReceivingYDS":"","ReceivingTD":"","RetTD":"","FumTD":"","2PT":"3","Fum":"9","FanPtsAgainst-pts":"15.60","TouchCarries":"139","TouchReceptions":"","Touches":"139","TargetsReceptions":"","Targets":"1","ReceptionPercentage":"","RzTarget":"1","RzTouch":"33","RzG2G":"20","Rank":9,"TotalPoints":"300.36"},{"PlayerName":"Kyler Murray","PlayerId":"2562382","Pos":"QB","Team":"ARI","PassingYDS":"3787","PassingTD":"24","PassingInt":"10","RushingYDS":"423","RushingTD":"5","ReceivingRec":"","ReceivingYDS":"7","ReceivingTD":"","RetTD":"","FumTD":"","2PT":"","Fum":"13","FanPtsAgainst-pts":"16.35","TouchCarries":"88","TouchReceptions":"","Touches":"88","TargetsReceptions":"","Targets":"","ReceptionPercentage":"","RzTarget":"","RzTouch":"25","RzG2G":"7","Rank":10,"TotalPoints":"286.21"},{"PlayerName":"Kirk Cousins","PlayerId":"2532820","Pos":"QB","Team":"MIN","PassingYDS":"4221","PassingTD":"33","PassingInt":"7","RushingYDS":"115","RushingTD":"1","ReceivingRec":"","ReceivingYDS":"","ReceivingTD":"","RetTD":"","FumTD":"","2PT":"","Fum":"12","FanPtsAgainst-pts":"16.42","TouchCarries":"29","TouchReceptions":"","Touches":"29","TargetsReceptions":"","Targets":"","ReceptionPercentage":"","RzTarget":"","RzTouch":"5","RzG2G":"4","Rank":11,"TotalPoints":"285.67"},{"PlayerName":"Ryan Tannehill","PlayerId":"2532956","Pos":"QB","Team":"TEN","PassingYDS":"3734","PassingTD":"21","PassingInt":"14","RushingYDS":"270","RushingTD":"7","ReceivingRec":"","ReceivingYDS":"","ReceivingTD":"","RetTD":"","FumTD":"","2PT":"1","Fum":"10","FanPtsAgainst-pts":"16.31","TouchCarries":"55","TouchReceptions":"","Touches":"55","TargetsReceptions":"","Targets":"","ReceptionPercentage":"","RzTarget":"","RzTouch":"14","RzG2G":"8","Rank":12,"TotalPoints":"261.33"},{"PlayerName":"Carson Wentz","PlayerId":"2555259","Pos":"QB","Team":"IND","PassingYDS":"3563","PassingTD":"27","PassingInt":"7","RushingYDS":"215","RushingTD":"1","ReceivingRec":"","ReceivingYDS":"","ReceivingTD":"","RetTD":"","FumTD":"","2PT":"2","Fum":"8","FanPtsAgainst-pts":"18.13","TouchCarries":"57","TouchReceptions":"","Touches":"57","TargetsReceptions":"","Targets":"","ReceptionPercentage":"","RzTarget":"","RzTouch":"9","RzG2G":"6","Rank":13,"TotalPoints":"252.82"},{"PlayerName":"Derek Carr","PlayerId":"2543499","Pos":"QB","Team":"LV","PassingYDS":"4804","PassingTD":"23","PassingInt":"14","RushingYDS":"108","RushingTD":"","ReceivingRec":"","ReceivingYDS":"","ReceivingTD":"","RetTD":"","FumTD":"","2PT":"","Fum":"13","FanPtsAgainst-pts":"16.64","TouchCarries":"40","TouchReceptions":"","Touches":"40","TargetsReceptions":"","Targets":"","ReceptionPercentage":"","RzTarget":"","RzTouch":"8","RzG2G":"4","Rank":14,"TotalPoints":"245.29"},{"PlayerName":"Lamar Jackson","PlayerId":"2560757","Pos":"QB","Team":"BAL","PassingYDS":"2882","PassingTD":"16","PassingInt":"13","RushingYDS":"767","RushingTD":"2","ReceivingRec":"","ReceivingYDS":"","ReceivingTD":"","RetTD":"","FumTD":"","2PT":"2","Fum":"6","FanPtsAgainst-pts":"16.26","TouchCarries":"133","TouchReceptions":"","Touches":"133","TargetsReceptions":"","Targets":"","ReceptionPercentage":"","RzTarget":"","RzTouch":"16","RzG2G":"6","Rank":15,"TotalPoints":"237.55"},{"PlayerName":"Russell Wilson","PlayerId":"2532975","Pos":"QB","Team":"SEA","PassingYDS":"3113","PassingTD":"25","PassingInt":"6","RushingYDS":"183","RushingTD":"2","ReceivingRec":"","ReceivingYDS":"","ReceivingTD":"","RetTD":"","FumTD":"","2PT":"1","Fum":"6","FanPtsAgainst-pts":"15.63","TouchCarries":"43","TouchReceptions":"","Touches":"43","TargetsReceptions":"","Targets":"","ReceptionPercentage":"","RzTarget":"","RzTouch":"7","RzG2G":"3","Rank":16,"TotalPoints":"235.05"},{"PlayerName":"Jimmy Garoppolo","PlayerId":"2543801","Pos":"QB","Team":"SF","PassingYDS":"3810","PassingTD":"20","PassingInt":"12","RushingYDS":"51","RushingTD":"3","ReceivingRec":"","ReceivingYDS":"","ReceivingTD":"","RetTD":"","FumTD":"","2PT":"1","Fum":"8","FanPtsAgainst-pts":"14.65","TouchCarries":"38","TouchReceptions":"","Touches":"38","TargetsReceptions":"","Targets":"","ReceptionPercentage":"","RzTarget":"","RzTouch":"3","RzG2G":"3","Rank":17,"TotalPoints":"220.33"},{"PlayerName":"Mac Jones","PlayerId":"2566334","Pos":"QB","Team":"NE","PassingYDS":"3801","PassingTD":"22","PassingInt":"13","RushingYDS":"129","RushingTD":"","ReceivingRec":"","ReceivingYDS":"","ReceivingTD":"","RetTD":"","FumTD":"","2PT":"2","Fum":"7","FanPtsAgainst-pts":"15.48","TouchCarries":"44","TouchReceptions":"","Touches":"44","TargetsReceptions":"","Targets":"","ReceptionPercentage":"","RzTarget":"","RzTouch":"7","RzG2G":"","Rank":18,"TotalPoints":"220.07"},{"PlayerName":"Taylor Heinicke","PlayerId":"2553656","Pos":"QB","Team":"WAS","PassingYDS":"3419","PassingTD":"20","PassingInt":"15","RushingYDS":"313","RushingTD":"1","ReceivingRec":"1","ReceivingYDS":"-2","ReceivingTD":"","RetTD":"","FumTD":"","2PT":"1","Fum":"7","FanPtsAgainst-pts":"16.39","TouchCarries":"60","TouchReceptions":"1","Touches":"61","TargetsReceptions":"1","Targets":"1","ReceptionPercentage":"100","RzTarget":"","RzTouch":"12","RzG2G":"8","Rank":19,"TotalPoints":"219.96"},{"PlayerName":"Matt Ryan","PlayerId":"310","Pos":"QB","Team":"ATL","PassingYDS":"3968","PassingTD":"20","PassingInt":"12","RushingYDS":"82","RushingTD":"1","ReceivingRec":"","ReceivingYDS":"","ReceivingTD":"","RetTD":"","FumTD":"","2PT":"1","Fum":"11","FanPtsAgainst-pts":"15.38","TouchCarries":"40","TouchReceptions":"","Touches":"40","TargetsReceptions":"","Targets":"","ReceptionPercentage":"","RzTarget":"","RzTouch":"11","RzG2G":"4","Rank":20,"TotalPoints":"211.62"},{"PlayerName":"Ben Roethlisberger","PlayerId":"2506109","Pos":"QB","Team":"PIT","PassingYDS":"3740","PassingTD":"22","PassingInt":"10","RushingYDS":"5","RushingTD":"1","ReceivingRec":"","ReceivingYDS":"","ReceivingTD":"","RetTD":"","FumTD":"","2PT":"2","Fum":"11","FanPtsAgainst-pts":"19.26","TouchCarries":"20","TouchReceptions":"","Touches":"20","TargetsReceptions":"","Targets":"","ReceptionPercentage":"","RzTarget":"","RzTouch":"5","RzG2G":"2","Rank":21,"TotalPoints":"211.10"},{"PlayerName":"Teddy Bridgewater","PlayerId":"2543465","Pos":"QB","Team":"DEN","PassingYDS":"3052","PassingTD":"18","PassingInt":"7","RushingYDS":"106","RushingTD":"2","ReceivingRec":"","ReceivingYDS":"","ReceivingTD":"","RetTD":"","FumTD":"","2PT":"1","Fum":"1","FanPtsAgainst-pts":"18.79","TouchCarries":"30","TouchReceptions":"","Touches":"30","TargetsReceptions":"","Targets":"","ReceptionPercentage":"","RzTarget":"","RzTouch":"11","RzG2G":"5","Rank":22,"TotalPoints":"202.68"},{"PlayerName":"Trevor Lawrence","PlayerId":"2566163","Pos":"QB","Team":"JAX","PassingYDS":"3641","PassingTD":"12","PassingInt":"17","RushingYDS":"334","RushingTD":"2","ReceivingRec":"","ReceivingYDS":"","ReceivingTD":"","RetTD":"","FumTD":"","2PT":"2","Fum":"9","FanPtsAgainst-pts":"16.94","TouchCarries":"73","TouchReceptions":"","Touches":"73","TargetsReceptions":"","Targets":"","ReceptionPercentage":"","RzTarget":"","RzTouch":"12","RzG2G":"5","Rank":23,"TotalPoints":"196.44"},{"PlayerName":"Jared Goff","PlayerId":"2555334","Pos":"QB","Team":"DET","PassingYDS":"3245","PassingTD":"19","PassingInt":"8","RushingYDS":"87","RushingTD":"","ReceivingRec":"","ReceivingYDS":"","ReceivingTD":"","RetTD":"","FumTD":"","2PT":"4","Fum":"9","FanPtsAgainst-pts":"17.39","TouchCarries":"17","TouchReceptions":"","Touches":"17","TargetsReceptions":"","Targets":"","ReceptionPercentage":"","RzTarget":"","RzTouch":"3","RzG2G":"3","Rank":24,"TotalPoints":"191.37"},{"PlayerName":"Baker Mayfield","PlayerId":"2560800","Pos":"QB","Team":"CLE","PassingYDS":"3010","PassingTD":"17","PassingInt":"13","RushingYDS":"134","RushingTD":"1","ReceivingRec":"","ReceivingYDS":"11","ReceivingTD":"","RetTD":"","FumTD":"","2PT":"2","Fum":"6","FanPtsAgainst-pts":"17.13","TouchCarries":"37","TouchReceptions":"","Touches":"37","TargetsReceptions":"","Targets":"","ReceptionPercentage":"","RzTarget":"","RzTouch":"4","RzG2G":"","Rank":25,"TotalPoints":"174.90"},{"PlayerName":"Tua Tagovailoa","PlayerId":"2564499","Pos":"QB","Team":"MIA","PassingYDS":"2653","PassingTD":"16","PassingInt":"10","RushingYDS":"128","RushingTD":"3","ReceivingRec":"","ReceivingYDS":"","ReceivingTD":"","RetTD":"","FumTD":"","2PT":"1","Fum":"9","FanPtsAgainst-pts":"12.42","TouchCarries":"42","TouchReceptions":"","Touches":"42","TargetsReceptions":"","Targets":"","ReceptionPercentage":"","RzTarget":"","RzTouch":"9","RzG2G":"3","Rank":26,"TotalPoints":"167.69"},{"PlayerName":"Daniel Jones","PlayerId":"2562299","Pos":"QB","Team":"NYG","PassingYDS":"2428","PassingTD":"10","PassingInt":"7","RushingYDS":"298","RushingTD":"2","ReceivingRec":"1","ReceivingYDS":"16","ReceivingTD":"","RetTD":"","FumTD":"","2PT":"3","Fum":"7","FanPtsAgainst-pts":"22.13","TouchCarries":"62","TouchReceptions":"1","Touches":"63","TargetsReceptions":"1","Targets":"1","ReceptionPercentage":"100","RzTarget":"","RzTouch":"13","RzG2G":"6","Rank":27,"TotalPoints":"160.65"},{"PlayerName":"Davis Mills","PlayerId":"2566136","Pos":"QB","Team":"HOU","PassingYDS":"2664","PassingTD":"16","PassingInt":"10","RushingYDS":"44","RushingTD":"","ReceivingRec":"","ReceivingYDS":"","ReceivingTD":"","RetTD":"","FumTD":"","2PT":"2","Fum":"5","FanPtsAgainst-pts":"16.38","TouchCarries":"18","TouchReceptions":"","Touches":"18","TargetsReceptions":"","Targets":"","ReceptionPercentage":"","RzTarget":"","RzTouch":"2","RzG2G":"","Rank":28,"TotalPoints":"152.96"},{"PlayerName":"Sam Darnold","PlayerId":"2561036","Pos":"QB","Team":"CAR","PassingYDS":"2527","PassingTD":"9","PassingInt":"13","RushingYDS":"222","RushingTD":"5","ReceivingRec":"","ReceivingYDS":"","ReceivingTD":"","RetTD":"","FumTD":"","2PT":"1","Fum":"9","FanPtsAgainst-pts":"16.95","TouchCarries":"48","TouchReceptions":"","Touches":"48","TargetsReceptions":"","Targets":"","ReceptionPercentage":"","RzTarget":"","RzTouch":"9","RzG2G":"4","Rank":29,"TotalPoints":"150.11"},{"PlayerName":"Zach Wilson","PlayerId":"2566391","Pos":"QB","Team":"NYJ","PassingYDS":"2334","PassingTD":"9","PassingInt":"11","RushingYDS":"185","RushingTD":"4","ReceivingRec":"","ReceivingYDS":"","ReceivingTD":"","RetTD":"","FumTD":"","2PT":"2","Fum":"5","FanPtsAgainst-pts":"10.63","TouchCarries":"29","TouchReceptions":"","Touches":"29","TargetsReceptions":"","Targets":"1","ReceptionPercentage":"","RzTarget":"1","RzTouch":"9","RzG2G":"7","Rank":30,"TotalPoints":"148.56"},{"PlayerName":"Taysom Hill","PlayerId":"2558954","Pos":"QB","Team":"NO","PassingYDS":"978","PassingTD":"4","PassingInt":"5","RushingYDS":"374","RushingTD":"5","ReceivingRec":"4","ReceivingYDS":"52","ReceivingTD":"","RetTD":"","FumTD":"","2PT":"","Fum":"2","FanPtsAgainst-pts":"18.97","TouchCarries":"70","TouchReceptions":"4","Touches":"74","TargetsReceptions":"4","Targets":"6","ReceptionPercentage":"67","RzTarget":"","RzTouch":"15","RzG2G":"4","Rank":31,"TotalPoints":"120.15"},{"PlayerName":"Jameis Winston","PlayerId":"2552033","Pos":"QB","Team":"NO","PassingYDS":"1170","PassingTD":"14","PassingInt":"3","RushingYDS":"166","RushingTD":"1","ReceivingRec":"","ReceivingYDS":"","ReceivingTD":"","RetTD":"","FumTD":"","2PT":"","Fum":"2","FanPtsAgainst-pts":"18.97","TouchCarries":"32","TouchReceptions":"","Touches":"32","TargetsReceptions":"","Targets":"","ReceptionPercentage":"","RzTarget":"","RzTouch":"4","RzG2G":"3","Rank":32,"TotalPoints":"118.10"},{"PlayerName":"Justin Fields","PlayerId":"2565920","Pos":"QB","Team":"CHI","PassingYDS":"1870","PassingTD":"7","PassingInt":"10","RushingYDS":"420","RushingTD":"2","ReceivingRec":"","ReceivingYDS":"","ReceivingTD":"","RetTD":"","FumTD":"","2PT":"","Fum":"12","FanPtsAgainst-pts":"18.10","TouchCarries":"72","TouchReceptions":"","Touches":"72","TargetsReceptions":"","Targets":"","ReceptionPercentage":"","RzTarget":"","RzTouch":"10","RzG2G":"6","Rank":33,"TotalPoints":"116.40"},{"PlayerName":"Andy Dalton","PlayerId":"2495143","Pos":"QB","Team":"CHI","PassingYDS":"1515","PassingTD":"8","PassingInt":"9","RushingYDS":"76","RushingTD":"","ReceivingRec":"","ReceivingYDS":"","ReceivingTD":"","RetTD":"","FumTD":"","2PT":"2","Fum":"1","FanPtsAgainst-pts":"18.10","TouchCarries":"16","TouchReceptions":"","Touches":"16","TargetsReceptions":"","Targets":"","ReceptionPercentage":"","RzTarget":"","RzTouch":"8","RzG2G":"5","Rank":34,"TotalPoints":"88.70"},{"PlayerName":"Trevor Siemian","PlayerId":"2553457","Pos":"QB","Team":"NO","PassingYDS":"1154","PassingTD":"11","PassingInt":"3","RushingYDS":"20","RushingTD":"1","ReceivingRec":"","ReceivingYDS":"","ReceivingTD":"","RetTD":"","FumTD":"","2PT":"","Fum":"3","FanPtsAgainst-pts":"18.97","TouchCarries":"9","TouchReceptions":"","Touches":"9","TargetsReceptions":"","Targets":"","ReceptionPercentage":"","RzTarget":"","RzTouch":"2","RzG2G":"","Rank":35,"TotalPoints":"87.16"},{"PlayerName":"Tyler Huntley","PlayerId":"2563560","Pos":"QB","Team":"BAL","PassingYDS":"1081","PassingTD":"3","PassingInt":"4","RushingYDS":"294","RushingTD":"2","ReceivingRec":"","ReceivingYDS":"","ReceivingTD":"","RetTD":"","FumTD":"","2PT":"","Fum":"4","FanPtsAgainst-pts":"16.26","TouchCarries":"47","TouchReceptions":"","Touches":"47","TargetsReceptions":"","Targets":"","ReceptionPercentage":"","RzTarget":"","RzTouch":"7","RzG2G":"1","Rank":36,"TotalPoints":"81.64"},{"PlayerName":"Cam Newton","PlayerId":"2495455","Pos":"QB","Team":"CAR","PassingYDS":"684","PassingTD":"4","PassingInt":"5","RushingYDS":"230","RushingTD":"5","ReceivingRec":"","ReceivingYDS":"","ReceivingTD":"","RetTD":"","FumTD":"","2PT":"1","Fum":"4","FanPtsAgainst-pts":"16.95","TouchCarries":"47","TouchReceptions":"","Touches":"47","TargetsReceptions":"","Targets":"","ReceptionPercentage":"","RzTarget":"","RzTouch":"9","RzG2G":"5","Rank":37,"TotalPoints":"81.03"},{"PlayerName":"Tyrod Taylor","PlayerId":"2495240","Pos":"QB","Team":"HOU","PassingYDS":"966","PassingTD":"5","PassingInt":"5","RushingYDS":"151","RushingTD":"3","ReceivingRec":"","ReceivingYDS":"","ReceivingTD":"","RetTD":"","FumTD":"","2PT":"","Fum":"3","FanPtsAgainst-pts":"16.38","TouchCarries":"19","TouchReceptions":"","Touches":"19","TargetsReceptions":"","Targets":"","ReceptionPercentage":"","RzTarget":"","RzTouch":"4","RzG2G":"3","Rank":38,"TotalPoints":"77.64"},{"PlayerName":"Jacoby Brissett","PlayerId":"2555261","Pos":"QB","Team":"MIA","PassingYDS":"1283","PassingTD":"5","PassingInt":"4","RushingYDS":"70","RushingTD":"1","ReceivingRec":"","ReceivingYDS":"","ReceivingTD":"","RetTD":"","FumTD":"","2PT":"1","Fum":"6","FanPtsAgainst-pts":"12.42","TouchCarries":"19","TouchReceptions":"","Touches":"19","TargetsReceptions":"","Targets":"","ReceptionPercentage":"","RzTarget":"","RzTouch":"3","RzG2G":"3","Rank":39,"TotalPoints":"68.32"},{"PlayerName":"Trey Lance","PlayerId":"2566532","Pos":"QB","Team":"SF","PassingYDS":"603","PassingTD":"5","PassingInt":"2","RushingYDS":"168","RushingTD":"1","ReceivingRec":"","ReceivingYDS":"","ReceivingTD":"","RetTD":"","FumTD":"","2PT":"1","Fum":"","FanPtsAgainst-pts":"14.65","TouchCarries":"38","TouchReceptions":"1","Touches":"39","TargetsReceptions":"1","Targets":"1","ReceptionPercentage":"100","RzTarget":"","RzTouch":"5","RzG2G":"2","Rank":40,"TotalPoints":"64.92"},{"PlayerName":"Geno Smith","PlayerId":"2539335","Pos":"QB","Team":"SEA","PassingYDS":"702","PassingTD":"5","PassingInt":"1","RushingYDS":"42","RushingTD":"1","ReceivingRec":"","ReceivingYDS":"","ReceivingTD":"","RetTD":"","FumTD":"","2PT":"","Fum":"1","FanPtsAgainst-pts":"15.63","TouchCarries":"9","TouchReceptions":"","Touches":"9","TargetsReceptions":"","Targets":"","ReceptionPercentage":"","RzTarget":"","RzTouch":"1","RzG2G":"1","Rank":41,"TotalPoints":"54.28"},{"PlayerName":"Drew Lock","PlayerId":"2562305","Pos":"QB","Team":"DEN","PassingYDS":"787","PassingTD":"2","PassingInt":"2","RushingYDS":"53","RushingTD":"2","ReceivingRec":"1","ReceivingYDS":"1","ReceivingTD":"","RetTD":"","FumTD":"","2PT":"","Fum":"2","FanPtsAgainst-pts":"18.79","TouchCarries":"10","TouchReceptions":"1","Touches":"11","TargetsReceptions":"1","Targets":"1","ReceptionPercentage":"100","RzTarget":"1","RzTouch":"3","RzG2G":"3","Rank":42,"TotalPoints":"51.08"},{"PlayerName":"Josh Johnson","PlayerId":"264","Pos":"QB","Team":"BAL","PassingYDS":"638","PassingTD":"5","PassingInt":"2","RushingYDS":"28","RushingTD":"","ReceivingRec":"","ReceivingYDS":"","ReceivingTD":"","RetTD":"","FumTD":"","2PT":"1","Fum":"2","FanPtsAgainst-pts":"16.26","TouchCarries":"9","TouchReceptions":"","Touches":"9","TargetsReceptions":"","Targets":"","ReceptionPercentage":"","RzTarget":"","RzTouch":"1","RzG2G":"","Rank":43,"TotalPoints":"45.89"},{"PlayerName":"Mike White","PlayerId":"2560929","Pos":"QB","Team":"NYJ","PassingYDS":"953","PassingTD":"5","PassingInt":"8","RushingYDS":"-1","RushingTD":"","ReceivingRec":"","ReceivingYDS":"","ReceivingTD":"","RetTD":"","FumTD":"","2PT":"1","Fum":"","FanPtsAgainst-pts":"10.63","TouchCarries":"5","TouchReceptions":"","Touches":"5","TargetsReceptions":"","Targets":"","ReceptionPercentage":"","RzTarget":"","RzTouch":"","RzG2G":"","Rank":44,"TotalPoints":"44.02"},{"PlayerName":"Colt McCoy","PlayerId":"497123","Pos":"QB","Team":"ARI","PassingYDS":"740","PassingTD":"3","PassingInt":"1","RushingYDS":"37","RushingTD":"","ReceivingRec":"","ReceivingYDS":"","ReceivingTD":"","RetTD":"","FumTD":"","2PT":"","Fum":"4","FanPtsAgainst-pts":"16.35","TouchCarries":"22","TouchReceptions":"","Touches":"22","TargetsReceptions":"","Targets":"","ReceptionPercentage":"","RzTarget":"","RzTouch":"6","RzG2G":"","Rank":45,"TotalPoints":"40.00"},{"PlayerName":"Gardner Minshew","PlayerId":"2562796","Pos":"QB","Team":"PHI","PassingYDS":"439","PassingTD":"4","PassingInt":"1","RushingYDS":"21","RushingTD":"","ReceivingRec":"","ReceivingYDS":"","ReceivingTD":"","RetTD":"","FumTD":"","2PT":"","Fum":"1","FanPtsAgainst-pts":"15.60","TouchCarries":"9","TouchReceptions":"","Touches":"9","TargetsReceptions":"","Targets":"","ReceptionPercentage":"","RzTarget":"","RzTouch":"","RzG2G":"","Rank":46,"TotalPoints":"32.66"},{"PlayerName":"Case Keenum","PlayerId":"2532888","Pos":"QB","Team":"CLE","PassingYDS":"462","PassingTD":"3","PassingInt":"1","RushingYDS":"22","RushingTD":"","ReceivingRec":"","ReceivingYDS":"","ReceivingTD":"","RetTD":"","FumTD":"","2PT":"","Fum":"1","FanPtsAgainst-pts":"17.13","TouchCarries":"12","TouchReceptions":"","Touches":"12","TargetsReceptions":"","Targets":"","ReceptionPercentage":"","RzTarget":"","RzTouch":"6","RzG2G":"2","Rank":47,"TotalPoints":"28.68"},{"PlayerName":"Mike Glennon","PlayerId":"2539275","Pos":"QB","Team":"NYG","PassingYDS":"790","PassingTD":"4","PassingInt":"10","RushingYDS":"33","RushingTD":"1","ReceivingRec":"","ReceivingYDS":"","ReceivingTD":"","RetTD":"","FumTD":"","2PT":"","Fum":"6","FanPtsAgainst-pts":"22.13","TouchCarries":"7","TouchReceptions":"","Touches":"7","TargetsReceptions":"","Targets":"","ReceptionPercentage":"","RzTarget":"","RzTouch":"1","RzG2G":"1","Rank":48,"TotalPoints":"28.30"},{"PlayerName":"Cooper Rush","PlayerId":"2559242","Pos":"QB","Team":"DAL","PassingYDS":"422","PassingTD":"3","PassingInt":"1","RushingYDS":"-8","RushingTD":"","ReceivingRec":"","ReceivingYDS":"","ReceivingTD":"","RetTD":"","FumTD":"","2PT":"","Fum":"1","FanPtsAgainst-pts":"15.27","TouchCarries":"9","TouchReceptions":"","Touches":"9","TargetsReceptions":"","Targets":"","ReceptionPercentage":"","RzTarget":"","RzTouch":"","RzG2G":"","Rank":49,"TotalPoints":"24.08"},{"PlayerName":"Joe Flacco","PlayerId":"382","Pos":"QB","Team":"NYJ","PassingYDS":"338","PassingTD":"3","PassingInt":"","RushingYDS":"3","RushingTD":"","ReceivingRec":"","ReceivingYDS":"","ReceivingTD":"","RetTD":"","FumTD":"","2PT":"","Fum":"1","FanPtsAgainst-pts":"10.63","TouchCarries":"2","TouchReceptions":"","Touches":"2","TargetsReceptions":"","Targets":"","ReceptionPercentage":"","RzTarget":"","RzTouch":"","RzG2G":"","Rank":50,"TotalPoints":"23.82"},{"PlayerName":"Tim Boyle","PlayerId":"2561187","Pos":"QB","Team":"DET","PassingYDS":"526","PassingTD":"3","PassingInt":"6","RushingYDS":"13","RushingTD":"","ReceivingRec":"","ReceivingYDS":"","ReceivingTD":"","RetTD":"","FumTD":"","2PT":"1","Fum":"1","FanPtsAgainst-pts":"17.39","TouchCarries":"2","TouchReceptions":"","Touches":"2","TargetsReceptions":"","Targets":"","ReceptionPercentage":"","RzTarget":"","RzTouch":"1","RzG2G":"","Rank":51,"TotalPoints":"23.34"},{"PlayerName":"Jordan Love","PlayerId":"2564007","Pos":"QB","Team":"GB","PassingYDS":"411","PassingTD":"2","PassingInt":"3","RushingYDS":"27","RushingTD":"","ReceivingRec":"","ReceivingYDS":"","ReceivingTD":"","RetTD":"","FumTD":"","2PT":"1","Fum":"3","FanPtsAgainst-pts":"17.47","TouchCarries":"12","TouchReceptions":"","Touches":"12","TargetsReceptions":"","Targets":"","ReceptionPercentage":"","RzTarget":"","RzTouch":"","RzG2G":"","Rank":52,"TotalPoints":"19.04"},{"PlayerName":"Mason Rudolph","PlayerId":"2560860","Pos":"QB","Team":"PIT","PassingYDS":"277","PassingTD":"1","PassingInt":"1","RushingYDS":"53","RushingTD":"","ReceivingRec":"","ReceivingYDS":"","ReceivingTD":"","RetTD":"","FumTD":"","2PT":"","Fum":"","FanPtsAgainst-pts":"19.26","TouchCarries":"5","TouchReceptions":"","Touches":"5","TargetsReceptions":"","Targets":"","ReceptionPercentage":"","RzTarget":"","RzTouch":"1","RzG2G":"","Rank":53,"TotalPoints":"18.38"},{"PlayerName":"Nick Foles","PlayerId":"2532842","Pos":"QB","Team":"CHI","PassingYDS":"250","PassingTD":"1","PassingInt":"","RushingYDS":"8","RushingTD":"","ReceivingRec":"","ReceivingYDS":"","ReceivingTD":"","RetTD":"","FumTD":"","2PT":"1","Fum":"1","FanPtsAgainst-pts":"18.10","TouchCarries":"4","TouchReceptions":"","Touches":"4","TargetsReceptions":"","Targets":"","ReceptionPercentage":"","RzTarget":"","RzTouch":"2","RzG2G":"","Rank":54,"TotalPoints":"14.80"},{"PlayerName":"Sean Mannion","PlayerId":"2552576","Pos":"QB","Team":"MIN","PassingYDS":"189","PassingTD":"1","PassingInt":"","RushingYDS":"14","RushingTD":"","ReceivingRec":"","ReceivingYDS":"","ReceivingTD":"","RetTD":"","FumTD":"","2PT":"","Fum":"","FanPtsAgainst-pts":"16.42","TouchCarries":"2","TouchReceptions":"","Touches":"2","TargetsReceptions":"","Targets":"","ReceptionPercentage":"","RzTarget":"","RzTouch":"","RzG2G":"","Rank":55,"TotalPoints":"12.96"},{"PlayerName":"Brandon Allen","PlayerId":"2555365","Pos":"QB","Team":"CIN","PassingYDS":"149","PassingTD":"2","PassingInt":"","RushingYDS":"-1","RushingTD":"","ReceivingRec":"","ReceivingYDS":"","ReceivingTD":"","RetTD":"","FumTD":"","2PT":"","Fum":"1","FanPtsAgainst-pts":"15.86","TouchCarries":"7","TouchReceptions":"","Touches":"7","TargetsReceptions":"","Targets":"","ReceptionPercentage":"","RzTarget":"","RzTouch":"2","RzG2G":"1","Rank":56,"TotalPoints":"12.86"},{"PlayerName":"Marcus Mariota","PlayerId":"2552466","Pos":"QB","Team":"LV","PassingYDS":"4","PassingTD":"","PassingInt":"","RushingYDS":"87","RushingTD":"1","ReceivingRec":"","ReceivingYDS":"","ReceivingTD":"","RetTD":"","FumTD":"","2PT":"","Fum":"1","FanPtsAgainst-pts":"16.64","TouchCarries":"13","TouchReceptions":"1","Touches":"14","TargetsReceptions":"1","Targets":"1","ReceptionPercentage":"100","RzTarget":"","RzTouch":"5","RzG2G":"3","Rank":57,"TotalPoints":"12.86"},{"PlayerName":"P.J. Walker","PlayerId":"2558904","Pos":"QB","Team":"CAR","PassingYDS":"362","PassingTD":"1","PassingInt":"3","RushingYDS":"13","RushingTD":"","ReceivingRec":"","ReceivingYDS":"","ReceivingTD":"","RetTD":"","FumTD":"","2PT":"1","Fum":"3","FanPtsAgainst-pts":"16.95","TouchCarries":"7","TouchReceptions":"","Touches":"7","TargetsReceptions":"","Targets":"","ReceptionPercentage":"","RzTarget":"","RzTouch":"","RzG2G":"","Rank":58,"TotalPoints":"12.45"},{"PlayerName":"Brian Hoyer","PlayerId":"81294","Pos":"QB","Team":"NE","PassingYDS":"227","PassingTD":"1","PassingInt":"","RushingYDS":"-8","RushingTD":"","ReceivingRec":"","ReceivingYDS":"","ReceivingTD":"","RetTD":"","FumTD":"","2PT":"","Fum":"","FanPtsAgainst-pts":"15.48","TouchCarries":"11","TouchReceptions":"","Touches":"11","TargetsReceptions":"","Targets":"","ReceptionPercentage":"","RzTarget":"","RzTouch":"","RzG2G":"","Rank":59,"TotalPoints":"12.28"},{"PlayerName":"Nick Mullens","PlayerId":"2558979","Pos":"QB","Team":"CLE","PassingYDS":"147","PassingTD":"1","PassingInt":"","RushingYDS":"","RushingTD":"","ReceivingRec":"","ReceivingYDS":"","ReceivingTD":"","RetTD":"","FumTD":"","2PT":"","Fum":"","FanPtsAgainst-pts":"17.13","TouchCarries":"","TouchReceptions":"","Touches":"","TargetsReceptions":"","Targets":"","ReceptionPercentage":"","RzTarget":"","RzTouch":"","RzG2G":"","Rank":60,"TotalPoints":"9.88"},{"PlayerName":"Jake Fromm","PlayerId":"2563608","Pos":"QB","Team":"NYG","PassingYDS":"210","PassingTD":"1","PassingInt":"3","RushingYDS":"65","RushingTD":"","ReceivingRec":"","ReceivingYDS":"","ReceivingTD":"","RetTD":"","FumTD":"","2PT":"","Fum":"2","FanPtsAgainst-pts":"22.13","TouchCarries":"8","TouchReceptions":"","Touches":"8","TargetsReceptions":"","Targets":"","ReceptionPercentage":"","RzTarget":"","RzTouch":"","RzG2G":"","Rank":61,"TotalPoints":"8.90"},{"PlayerName":"Mitchell Trubisky","PlayerId":"2558008","Pos":"QB","Team":"BUF","PassingYDS":"43","PassingTD":"","PassingInt":"1","RushingYDS":"24","RushingTD":"1","ReceivingRec":"","ReceivingYDS":"","ReceivingTD":"","RetTD":"","FumTD":"","2PT":"","Fum":"","FanPtsAgainst-pts":"18.22","TouchCarries":"13","TouchReceptions":"","Touches":"13","TargetsReceptions":"","Targets":"","ReceptionPercentage":"","RzTarget":"","RzTouch":"1","RzG2G":"1","Rank":62,"TotalPoints":"8.12"},{"PlayerName":"Kyle Allen","PlayerId":"2561177","Pos":"QB","Team":"WAS","PassingYDS":"120","PassingTD":"1","PassingInt":"","RushingYDS":"11","RushingTD":"","ReceivingRec":"","ReceivingYDS":"","ReceivingTD":"","RetTD":"","FumTD":"","2PT":"","Fum":"1","FanPtsAgainst-pts":"16.39","TouchCarries":"2","TouchReceptions":"","Touches":"2","TargetsReceptions":"","Targets":"","ReceptionPercentage":"","RzTarget":"","RzTouch":"1","RzG2G":"1","Rank":63,"TotalPoints":"7.90"},{"PlayerName":"Garrett Gilbert","PlayerId":"2549982","Pos":"QB","Team":"WAS","PassingYDS":"194","PassingTD":"","PassingInt":"","RushingYDS":"","RushingTD":"","ReceivingRec":"","ReceivingYDS":"","ReceivingTD":"","RetTD":"","FumTD":"","2PT":"","Fum":"1","FanPtsAgainst-pts":"16.39","TouchCarries":"","TouchReceptions":"","Touches":"","TargetsReceptions":"","Targets":"","ReceptionPercentage":"","RzTarget":"","RzTouch":"","RzG2G":"","Rank":64,"TotalPoints":"5.76"},{"PlayerName":"Ian Book","PlayerId":"2566352","Pos":"QB","Team":"NO","PassingYDS":"135","PassingTD":"","PassingInt":"2","RushingYDS":"6","RushingTD":"","ReceivingRec":"","ReceivingYDS":"","ReceivingTD":"","RetTD":"","FumTD":"","2PT":"","Fum":"","FanPtsAgainst-pts":"18.97","TouchCarries":"3","TouchReceptions":"","Touches":"3","TargetsReceptions":"","Targets":"","ReceptionPercentage":"","RzTarget":"","RzTouch":"","RzG2G":"","Rank":65,"TotalPoints":"2.00"},{"PlayerName":"Blaine Gabbert","PlayerId":"2495441","Pos":"QB","Team":"TB","PassingYDS":"67","PassingTD":"","PassingInt":"","RushingYDS":"-7","RushingTD":"","ReceivingRec":"","ReceivingYDS":"","ReceivingTD":"","RetTD":"","FumTD":"","2PT":"","Fum":"","FanPtsAgainst-pts":"15.29","TouchCarries":"9","TouchReceptions":"","Touches":"9","TargetsReceptions":"","Targets":"","ReceptionPercentage":"","RzTarget":"","RzTouch":"3","RzG2G":"3","Rank":66,"TotalPoints":"1.98"},{"PlayerName":"C.J. Beathard","PlayerId":"2557922","Pos":"QB","Team":"JAX","PassingYDS":"33","PassingTD":"","PassingInt":"","RushingYDS":"2","RushingTD":"","ReceivingRec":"","ReceivingYDS":"","ReceivingTD":"","RetTD":"","FumTD":"","2PT":"","Fum":"","FanPtsAgainst-pts":"16.94","TouchCarries":"1","TouchReceptions":"","Touches":"1","TargetsReceptions":"","Targets":"","ReceptionPercentage":"","RzTarget":"","RzTouch":"","RzG2G":"","Rank":67,"TotalPoints":"1.52"},{"PlayerName":"Chad Henne","PlayerId":"252","Pos":"QB","Team":"KC","PassingYDS":"82","PassingTD":"","PassingInt":"","RushingYDS":"","RushingTD":"","ReceivingRec":"","ReceivingYDS":"","ReceivingTD":"","RetTD":"","FumTD":"","2PT":"","Fum":"2","FanPtsAgainst-pts":"14.22","TouchCarries":"8","TouchReceptions":"","Touches":"8","TargetsReceptions":"","Targets":"","ReceptionPercentage":"","RzTarget":"","RzTouch":"2","RzG2G":"2","Rank":68,"TotalPoints":"1.08"},{"PlayerName":"Sam Ehlinger","PlayerId":"2566142","Pos":"QB","Team":"IND","PassingYDS":"","PassingTD":"","PassingInt":"","RushingYDS":"9","RushingTD":"","ReceivingRec":"","ReceivingYDS":"","ReceivingTD":"","RetTD":"","FumTD":"","2PT":"","Fum":"","FanPtsAgainst-pts":"18.13","TouchCarries":"3","TouchReceptions":"","Touches":"3","TargetsReceptions":"","Targets":"","ReceptionPercentage":"","RzTarget":"","RzTouch":"1","RzG2G":"1","Rank":69,"TotalPoints":"0.90"},{"PlayerName":"Kellen Mond","PlayerId":"2566310","Pos":"QB","Team":"MIN","PassingYDS":"5","PassingTD":"","PassingInt":"","RushingYDS":"","RushingTD":"","ReceivingRec":"","ReceivingYDS":"","ReceivingTD":"","RetTD":"","FumTD":"","2PT":"","Fum":"","FanPtsAgainst-pts":"16.42","TouchCarries":"","TouchReceptions":"","Touches":"","TargetsReceptions":"","Targets":"","ReceptionPercentage":"","RzTarget":"","RzTouch":"","RzG2G":"","Rank":70,"TotalPoints":"0.20"},{"PlayerName":"Nathan Peterman","PlayerId":"2558191","Pos":"QB","Team":"LV","PassingYDS":"","PassingTD":"","PassingInt":"","RushingYDS":"2","RushingTD":"","ReceivingRec":"","ReceivingYDS":"","ReceivingTD":"","RetTD":"","FumTD":"","2PT":"","Fum":"","FanPtsAgainst-pts":"16.64","TouchCarries":"2","TouchReceptions":"","Touches":"2","TargetsReceptions":"","Targets":"","ReceptionPercentage":"","RzTarget":"","RzTouch":"","RzG2G":"","Rank":71,"TotalPoints":"0.20"},{"PlayerName":"Kenji Bahar","PlayerId":"2566608","Pos":"QB","Team":"FA","PassingYDS":"","PassingTD":"","PassingInt":"","RushingYDS":"","RushingTD":"","ReceivingRec":"","ReceivingYDS":"","ReceivingTD":"","RetTD":"","FumTD":"","2PT":"","Fum":"","FanPtsAgainst-pts":null,"TouchCarries":null,"TouchReceptions":null,"Touches":null,"TargetsReceptions":null,"Targets":null,"ReceptionPercentage":null,"RzTarget":null,"RzTouch":null,"RzG2G":null,"Rank":72,"TotalPoints":"0.00"},{"PlayerName":"Matt Barkley","PlayerId":"2539308","Pos":"QB","Team":"ATL","PassingYDS":"","PassingTD":"","PassingInt":"","RushingYDS":"","RushingTD":"","ReceivingRec":"","ReceivingYDS":"","ReceivingTD":"","RetTD":"","FumTD":"","2PT":"","Fum":"","FanPtsAgainst-pts":"15.38","TouchCarries":"","TouchReceptions":"","Touches":"","TargetsReceptions":"","Targets":"","ReceptionPercentage":"","RzTarget":"","RzTouch":"","RzG2G":"","Rank":73,"TotalPoints":"0.00"},{"PlayerName":"Blake Bortles","PlayerId":"2543477","Pos":"QB","Team":"NO","PassingYDS":"","PassingTD":"","PassingInt":"","RushingYDS":"","RushingTD":"","ReceivingRec":"","ReceivingYDS":"","ReceivingTD":"","RetTD":"","FumTD":"","2PT":"","Fum":"","FanPtsAgainst-pts":"18.97","TouchCarries":"","TouchReceptions":"","Touches":"","TargetsReceptions":"","Targets":"","ReceptionPercentage":"","RzTarget":"","RzTouch":"","RzG2G":"","Rank":74,"TotalPoints":"0.00"},{"PlayerName":"Drew Brees","PlayerId":"2504775","Pos":"QB","Team":"FA","PassingYDS":"","PassingTD":"","PassingInt":"","RushingYDS":"","RushingTD":"","ReceivingRec":"","ReceivingYDS":"","ReceivingTD":"","RetTD":"","FumTD":"","2PT":"","Fum":"","FanPtsAgainst-pts":null,"TouchCarries":null,"TouchReceptions":null,"Touches":null,"TargetsReceptions":null,"Targets":null,"ReceptionPercentage":null,"RzTarget":null,"RzTouch":null,"RzG2G":null,"Rank":75,"TotalPoints":"0.00"},{"PlayerName":"Jake Browning","PlayerId":"2562634","Pos":"QB","Team":"CIN","PassingYDS":"","PassingTD":"","PassingInt":"","RushingYDS":"","RushingTD":"","ReceivingRec":"","ReceivingYDS":"","ReceivingTD":"","RetTD":"","FumTD":"","2PT":"","Fum":"","FanPtsAgainst-pts":"15.86","TouchCarries":"","TouchReceptions":"","Touches":"","TargetsReceptions":"","Targets":"","ReceptionPercentage":"","RzTarget":"","RzTouch":"","RzG2G":"","Rank":76,"TotalPoints":"0.00"},{"PlayerName":"Shane Buechele","PlayerId":"2566983","Pos":"QB","Team":"KC","PassingYDS":"","PassingTD":"","PassingInt":"","RushingYDS":"","RushingTD":"","ReceivingRec":"","ReceivingYDS":"","ReceivingTD":"","RetTD":"","FumTD":"","2PT":"","Fum":"","FanPtsAgainst-pts":"14.22","TouchCarries":"","TouchReceptions":"","Touches":"","TargetsReceptions":"","Targets":"","ReceptionPercentage":"","RzTarget":"","RzTouch":"","RzG2G":"","Rank":77,"TotalPoints":"0.00"},{"PlayerName":"Ben DiNucci","PlayerId":"2563839","Pos":"QB","Team":"DAL","PassingYDS":"","PassingTD":"","PassingInt":"","RushingYDS":"","RushingTD":"","ReceivingRec":"","ReceivingYDS":"","ReceivingTD":"","RetTD":"","FumTD":"","2PT":"","Fum":"","FanPtsAgainst-pts":"15.27","TouchCarries":"","TouchReceptions":"","Touches":"","TargetsReceptions":"","Targets":"","ReceptionPercentage":"","RzTarget":"","RzTouch":"","RzG2G":"","Rank":78,"TotalPoints":"0.00"},{"PlayerName":"Joshua Dobbs","PlayerId":"2558167","Pos":"QB","Team":"PIT","PassingYDS":"","PassingTD":"","PassingInt":"","RushingYDS":"","RushingTD":"","ReceivingRec":"","ReceivingYDS":"","ReceivingTD":"","RetTD":"","FumTD":"","2PT":"","Fum":"","FanPtsAgainst-pts":"19.26","TouchCarries":"","TouchReceptions":"","Touches":"","TargetsReceptions":"","Targets":"","ReceptionPercentage":"","RzTarget":"","RzTouch":"","RzG2G":"","Rank":79,"TotalPoints":"0.00"},{"PlayerName":"Jeff Driskel","PlayerId":"2555262","Pos":"QB","Team":"HOU","PassingYDS":"","PassingTD":"","PassingInt":"","RushingYDS":"","RushingTD":"","ReceivingRec":"","ReceivingYDS":"","ReceivingTD":"","RetTD":"","FumTD":"","2PT":"","Fum":"","FanPtsAgainst-pts":"16.38","TouchCarries":"","TouchReceptions":"","Touches":"","TargetsReceptions":"","Targets":"","ReceptionPercentage":"","RzTarget":"","RzTouch":"","RzG2G":"","Rank":80,"TotalPoints":"0.00"},{"PlayerName":"Danny Etling","PlayerId":"2560717","Pos":"QB","Team":"JAX","PassingYDS":"","PassingTD":"","PassingInt":"","RushingYDS":"","RushingTD":"","ReceivingRec":"","ReceivingYDS":"","ReceivingTD":"","RetTD":"","FumTD":"","2PT":"","Fum":"","FanPtsAgainst-pts":"16.94","TouchCarries":"","TouchReceptions":"","Touches":"","TargetsReceptions":"","Targets":"","ReceptionPercentage":"","RzTarget":"","RzTouch":"","RzG2G":"","Rank":81,"TotalPoints":"0.00"},{"PlayerName":"Ryan Finley","PlayerId":"2562651","Pos":"QB","Team":"FA","PassingYDS":"","PassingTD":"","PassingInt":"","RushingYDS":"","RushingTD":"","ReceivingRec":"","ReceivingYDS":"","ReceivingTD":"","RetTD":"","FumTD":"","2PT":"","Fum":"","FanPtsAgainst-pts":null,"TouchCarries":null,"TouchReceptions":null,"Touches":null,"TargetsReceptions":null,"Targets":null,"ReceptionPercentage":null,"RzTarget":null,"RzTouch":null,"RzG2G":null,"Rank":82,"TotalPoints":"0.00"},{"PlayerName":"Anthony Gordon","PlayerId":"2565153","Pos":"QB","Team":"DEN","PassingYDS":"","PassingTD":"","PassingInt":"","RushingYDS":"","RushingTD":"","ReceivingRec":"","ReceivingYDS":"","ReceivingTD":"","RetTD":"","FumTD":"","2PT":"","Fum":"","FanPtsAgainst-pts":"18.79","TouchCarries":"","TouchReceptions":"","Touches":"","TargetsReceptions":"","Targets":"","ReceptionPercentage":"","RzTarget":"","RzTouch":"","RzG2G":"","Rank":83,"TotalPoints":"0.00"},{"PlayerName":"Will Grier","PlayerId":"2562404","Pos":"QB","Team":"DAL","PassingYDS":"","PassingTD":"","PassingInt":"","RushingYDS":"","RushingTD":"","ReceivingRec":"","ReceivingYDS":"","ReceivingTD":"","RetTD":"","FumTD":"","2PT":"","Fum":"","FanPtsAgainst-pts":"15.27","TouchCarries":"","TouchReceptions":"","Touches":"","TargetsReceptions":"","Targets":"","ReceptionPercentage":"","RzTarget":"","RzTouch":"","RzG2G":"","Rank":84,"TotalPoints":"0.00"},{"PlayerName":"Ryan Griffin","PlayerId":"2541185","Pos":"QB","Team":"TB","PassingYDS":"","PassingTD":"","PassingInt":"","RushingYDS":"","RushingTD":"","ReceivingRec":"","ReceivingYDS":"","ReceivingTD":"","RetTD":"","FumTD":"","2PT":"","Fum":"","FanPtsAgainst-pts":"15.29","TouchCarries":"","TouchReceptions":"","Touches":"","TargetsReceptions":"","Targets":"","ReceptionPercentage":"","RzTarget":"","RzTouch":"","RzG2G":"","Rank":85,"TotalPoints":"0.00"},{"PlayerName":"Dwayne Haskins","PlayerId":"2562660","Pos":"QB","Team":"PIT","PassingYDS":"","PassingTD":"","PassingInt":"","RushingYDS":"","RushingTD":"","ReceivingRec":"","ReceivingYDS":"","ReceivingTD":"","RetTD":"","FumTD":"","2PT":"","Fum":"","FanPtsAgainst-pts":"19.26","TouchCarries":"","TouchReceptions":"1","Touches":"1","TargetsReceptions":"1","Targets":"1","ReceptionPercentage":"100","RzTarget":"","RzTouch":"","RzG2G":"","Rank":86,"TotalPoints":"0.00"},{"PlayerName":"Devlin Hodges","PlayerId":"2563258","Pos":"QB","Team":"FA","PassingYDS":"","PassingTD":"","PassingInt":"","RushingYDS":"","RushingTD":"","ReceivingRec":"","ReceivingYDS":"","ReceivingTD":"","RetTD":"","FumTD":"","2PT":"","Fum":"","FanPtsAgainst-pts":null,"TouchCarries":null,"TouchReceptions":null,"Touches":null,"TargetsReceptions":null,"Targets":null,"ReceptionPercentage":null,"RzTarget":null,"RzTouch":null,"RzG2G":null,"Rank":87,"TotalPoints":"0.00"},{"PlayerName":"Brett Hundley","PlayerId":"2552588","Pos":"QB","Team":"IND","PassingYDS":"","PassingTD":"","PassingInt":"","RushingYDS":"","RushingTD":"","ReceivingRec":"","ReceivingYDS":"","ReceivingTD":"","RetTD":"","FumTD":"","2PT":"","Fum":"","FanPtsAgainst-pts":"18.13","TouchCarries":"","TouchReceptions":"","Touches":"","TargetsReceptions":"","Targets":"","ReceptionPercentage":"","RzTarget":"","RzTouch":"","RzG2G":"","Rank":88,"TotalPoints":"0.00"},{"PlayerName":"Colin Kaepernick","PlayerId":"2495186","Pos":"QB","Team":"FA","PassingYDS":"","PassingTD":"","PassingInt":"","RushingYDS":"","RushingTD":"","ReceivingRec":"","ReceivingYDS":"","ReceivingTD":"","RetTD":"","FumTD":"","2PT":"","Fum":"","FanPtsAgainst-pts":null,"TouchCarries":null,"TouchReceptions":null,"Touches":null,"TargetsReceptions":null,"Targets":null,"ReceptionPercentage":null,"RzTarget":null,"RzTouch":null,"RzG2G":null,"Rank":89,"TotalPoints":"0.00"},{"PlayerName":"DeShone Kizer","PlayerId":"2557983","Pos":"QB","Team":"FA","PassingYDS":"","PassingTD":"","PassingInt":"","RushingYDS":"","RushingTD":"","ReceivingRec":"","ReceivingYDS":"","ReceivingTD":"","RetTD":"","FumTD":"","2PT":"","Fum":"","FanPtsAgainst-pts":null,"TouchCarries":null,"TouchReceptions":null,"Touches":null,"TargetsReceptions":null,"Targets":null,"ReceptionPercentage":null,"RzTarget":null,"RzTouch":null,"RzG2G":null,"Rank":90,"TotalPoints":"0.00"},{"PlayerName":"Kyle Lauletta","PlayerId":"2560786","Pos":"QB","Team":"FA","PassingYDS":"","PassingTD":"","PassingInt":"","RushingYDS":"","RushingTD":"","ReceivingRec":"","ReceivingYDS":"","ReceivingTD":"","RetTD":"","FumTD":"","2PT":"","Fum":"","FanPtsAgainst-pts":null,"TouchCarries":null,"TouchReceptions":null,"Touches":null,"TargetsReceptions":null,"Targets":null,"ReceptionPercentage":null,"RzTarget":null,"RzTouch":null,"RzG2G":null,"Rank":91,"TotalPoints":"0.00"},{"PlayerName":"Jake Luton","PlayerId":"2564205","Pos":"QB","Team":"MIA","PassingYDS":"","PassingTD":"","PassingInt":"","RushingYDS":"","RushingTD":"","ReceivingRec":"","ReceivingYDS":"","ReceivingTD":"","RetTD":"","FumTD":"","2PT":"","Fum":"","FanPtsAgainst-pts":"12.42","TouchCarries":"","TouchReceptions":"","Touches":"","TargetsReceptions":"","Targets":"","ReceptionPercentage":"","RzTarget":"","RzTouch":"","RzG2G":"","Rank":92,"TotalPoints":"0.00"},{"PlayerName":"AJ McCarron","PlayerId":"2543497","Pos":"QB","Team":"ATL","PassingYDS":"","PassingTD":"","PassingInt":"","RushingYDS":"","RushingTD":"","ReceivingRec":"","ReceivingYDS":"","ReceivingTD":"","RetTD":"","FumTD":"","2PT":"","Fum":"","FanPtsAgainst-pts":"15.38","TouchCarries":"","TouchReceptions":"","Touches":"","TargetsReceptions":"","Targets":"","ReceptionPercentage":"","RzTarget":"","RzTouch":"","RzG2G":"","Rank":93,"TotalPoints":"0.00"},{"PlayerName":"Josh McCown","PlayerId":"2505076","Pos":"QB","Team":"FA","PassingYDS":"","PassingTD":"","PassingInt":"","RushingYDS":"","RushingTD":"","ReceivingRec":"","ReceivingYDS":"","ReceivingTD":"","RetTD":"","FumTD":"","2PT":"","Fum":"","FanPtsAgainst-pts":null,"TouchCarries":null,"TouchReceptions":null,"Touches":null,"TargetsReceptions":null,"Targets":null,"ReceptionPercentage":null,"RzTarget":null,"RzTouch":null,"RzG2G":null,"Rank":94,"TotalPoints":"0.00"},{"PlayerName":"Cole McDonald","PlayerId":"2564052","Pos":"QB","Team":"FA","PassingYDS":"","PassingTD":"","PassingInt":"","RushingYDS":"","RushingTD":"","ReceivingRec":"","ReceivingYDS":"","ReceivingTD":"","RetTD":"","FumTD":"","2PT":"","Fum":"","FanPtsAgainst-pts":null,"TouchCarries":null,"TouchReceptions":null,"Touches":null,"TargetsReceptions":null,"Targets":null,"ReceptionPercentage":null,"RzTarget":null,"RzTouch":null,"RzG2G":null,"Rank":95,"TotalPoints":"0.00"},{"PlayerName":"Alex McGough","PlayerId":"2561148","Pos":"QB","Team":"FA","PassingYDS":"","PassingTD":"","PassingInt":"","RushingYDS":"","RushingTD":"","ReceivingRec":"","ReceivingYDS":"","ReceivingTD":"","RetTD":"","FumTD":"","2PT":"","Fum":"","FanPtsAgainst-pts":null,"TouchCarries":null,"TouchReceptions":null,"Touches":null,"TargetsReceptions":null,"Targets":null,"ReceptionPercentage":null,"RzTarget":null,"RzTouch":null,"RzG2G":null,"Rank":96,"TotalPoints":"0.00"},{"PlayerName":"Trace McSorley","PlayerId":"2562403","Pos":"QB","Team":"ARI","PassingYDS":"","PassingTD":"","PassingInt":"","RushingYDS":"","RushingTD":"","ReceivingRec":"","ReceivingYDS":"","ReceivingTD":"","RetTD":"","FumTD":"","2PT":"","Fum":"","FanPtsAgainst-pts":"16.35","TouchCarries":"","TouchReceptions":"","Touches":"","TargetsReceptions":"","Targets":"","ReceptionPercentage":"","RzTarget":"","RzTouch":"","RzG2G":"","Rank":97,"TotalPoints":"0.00"},{"PlayerName":"Steven Montez","PlayerId":"2565285","Pos":"QB","Team":"DET","PassingYDS":"","PassingTD":"","PassingInt":"","RushingYDS":"","RushingTD":"","ReceivingRec":"","ReceivingYDS":"","ReceivingTD":"","RetTD":"","FumTD":"","2PT":"","Fum":"","FanPtsAgainst-pts":"17.39","TouchCarries":"","TouchReceptions":"","Touches":"","TargetsReceptions":"","Targets":"","ReceptionPercentage":"","RzTarget":"","RzTouch":"","RzG2G":"","Rank":98,"TotalPoints":"0.00"},{"PlayerName":"Matt Moore","PlayerId":"2507282","Pos":"QB","Team":"FA","PassingYDS":"","PassingTD":"","PassingInt":"","RushingYDS":"","RushingTD":"","ReceivingRec":"","ReceivingYDS":"","ReceivingTD":"","RetTD":"","FumTD":"","2PT":"","Fum":"","FanPtsAgainst-pts":null,"TouchCarries":null,"TouchReceptions":null,"Touches":null,"TargetsReceptions":null,"Targets":null,"ReceptionPercentage":null,"RzTarget":null,"RzTouch":null,"RzG2G":null,"Rank":99,"TotalPoints":"0.00"},{"PlayerName":"James Morgan","PlayerId":"2564805","Pos":"QB","Team":"IND","PassingYDS":"","PassingTD":"","PassingInt":"","RushingYDS":"","RushingTD":"","ReceivingRec":"","ReceivingYDS":"","ReceivingTD":"","RetTD":"","FumTD":"","2PT":"","Fum":"","FanPtsAgainst-pts":"18.13","TouchCarries":"","TouchReceptions":"","Touches":"","TargetsReceptions":"","Targets":"","ReceptionPercentage":"","RzTarget":"","RzTouch":"","RzG2G":"","Rank":100,"TotalPoints":"0.00"},{"PlayerName":"Jalen Morton","PlayerId":"2564013","Pos":"QB","Team":"FA","PassingYDS":"","PassingTD":"","PassingInt":"","RushingYDS":"","RushingTD":"","ReceivingRec":"","ReceivingYDS":"","ReceivingTD":"","RetTD":"","FumTD":"","2PT":"","Fum":"","FanPtsAgainst-pts":null,"TouchCarries":null,"TouchReceptions":null,"Touches":null,"TargetsReceptions":null,"Targets":null,"ReceptionPercentage":null,"RzTarget":null,"RzTouch":null,"RzG2G":null,"Rank":101,"TotalPoints":"0.00"},{"PlayerName":"Jamie Newman","PlayerId":"2567058","Pos":"QB","Team":"FA","PassingYDS":"","PassingTD":"","PassingInt":"","RushingYDS":"","RushingTD":"","ReceivingRec":"","ReceivingYDS":"","ReceivingTD":"","RetTD":"","FumTD":"","2PT":"","Fum":"","FanPtsAgainst-pts":null,"TouchCarries":null,"TouchReceptions":null,"Touches":null,"TargetsReceptions":null,"Targets":null,"ReceptionPercentage":null,"RzTarget":null,"RzTouch":null,"RzG2G":null,"Rank":102,"TotalPoints":"0.00"},{"PlayerName":"Bryce Perkins","PlayerId":"2564382","Pos":"QB","Team":"LA","PassingYDS":"","PassingTD":"","PassingInt":"","RushingYDS":"","RushingTD":"","ReceivingRec":"","ReceivingYDS":"","ReceivingTD":"","RetTD":"","FumTD":"","2PT":"","Fum":"","FanPtsAgainst-pts":"16.38","TouchCarries":"1","TouchReceptions":"","Touches":"1","TargetsReceptions":"","Targets":"","ReceptionPercentage":"","RzTarget":"","RzTouch":"","RzG2G":"","Rank":103,"TotalPoints":"0.00"},{"PlayerName":"Philip Rivers","PlayerId":"2506121","Pos":"QB","Team":"FA","PassingYDS":"","PassingTD":"","PassingInt":"","RushingYDS":"","RushingTD":"","ReceivingRec":"","ReceivingYDS":"","ReceivingTD":"","RetTD":"","FumTD":"","2PT":"","Fum":"","FanPtsAgainst-pts":null,"TouchCarries":null,"TouchReceptions":null,"Touches":null,"TargetsReceptions":null,"Targets":null,"ReceptionPercentage":null,"RzTarget":null,"RzTouch":null,"RzG2G":null,"Rank":104,"TotalPoints":"0.00"},{"PlayerName":"Jake Rudock","PlayerId":"2556232","Pos":"QB","Team":"FA","PassingYDS":"","PassingTD":"","PassingInt":"","RushingYDS":"","RushingTD":"","ReceivingRec":"","ReceivingYDS":"","ReceivingTD":"","RetTD":"","FumTD":"","2PT":"","Fum":"","FanPtsAgainst-pts":null,"TouchCarries":null,"TouchReceptions":null,"Touches":null,"TargetsReceptions":null,"Targets":null,"ReceptionPercentage":null,"RzTarget":null,"RzTouch":null,"RzG2G":null,"Rank":105,"TotalPoints":"0.00"},{"PlayerName":"Brett Rypien","PlayerId":"2562718","Pos":"QB","Team":"DEN","PassingYDS":"","PassingTD":"","PassingInt":"","RushingYDS":"","RushingTD":"","ReceivingRec":"","ReceivingYDS":"","ReceivingTD":"","RetTD":"","FumTD":"","2PT":"","Fum":"","FanPtsAgainst-pts":"18.79","TouchCarries":"","TouchReceptions":"","Touches":"","TargetsReceptions":"","Targets":"","ReceptionPercentage":"","RzTarget":"","RzTouch":"","RzG2G":"","Rank":106,"TotalPoints":"0.00"},{"PlayerName":"Matt Schaub","PlayerId":"2505982","Pos":"QB","Team":"FA","PassingYDS":"","PassingTD":"","PassingInt":"","RushingYDS":"","RushingTD":"","ReceivingRec":"","ReceivingYDS":"","ReceivingTD":"","RetTD":"","FumTD":"","2PT":"","Fum":"","FanPtsAgainst-pts":null,"TouchCarries":null,"TouchReceptions":null,"Touches":null,"TargetsReceptions":null,"Targets":null,"ReceptionPercentage":null,"RzTarget":null,"RzTouch":null,"RzG2G":null,"Rank":107,"TotalPoints":"0.00"},{"PlayerName":"Kyle Shurmur","PlayerId":"2562731","Pos":"QB","Team":"FA","PassingYDS":"","PassingTD":"","PassingInt":"","RushingYDS":"","RushingTD":"","ReceivingRec":"","ReceivingYDS":"","ReceivingTD":"","RetTD":"","FumTD":"","2PT":"","Fum":"","FanPtsAgainst-pts":null,"TouchCarries":null,"TouchReceptions":null,"Touches":null,"TargetsReceptions":null,"Targets":null,"ReceptionPercentage":null,"RzTarget":null,"RzTouch":null,"RzG2G":null,"Rank":108,"TotalPoints":"0.00"},{"PlayerName":"Reid Sinnett","PlayerId":"2565255","Pos":"QB","Team":"PHI","PassingYDS":"","PassingTD":"","PassingInt":"","RushingYDS":"","RushingTD":"","ReceivingRec":"","ReceivingYDS":"","ReceivingTD":"","RetTD":"","FumTD":"","2PT":"","Fum":"","FanPtsAgainst-pts":"15.60","TouchCarries":"","TouchReceptions":"","Touches":"","TargetsReceptions":"","Targets":"","ReceptionPercentage":"","RzTarget":"","RzTouch":"","RzG2G":"","Rank":109,"TotalPoints":"0.00"},{"PlayerName":"Alex Smith","PlayerId":"2506340","Pos":"QB","Team":"FA","PassingYDS":"","PassingTD":"","PassingInt":"","RushingYDS":"","RushingTD":"","ReceivingRec":"","ReceivingYDS":"","ReceivingTD":"","RetTD":"","FumTD":"","2PT":"","Fum":"","FanPtsAgainst-pts":null,"TouchCarries":null,"TouchReceptions":null,"Touches":null,"TargetsReceptions":null,"Targets":null,"ReceptionPercentage":null,"RzTarget":null,"RzTouch":null,"RzG2G":null,"Rank":110,"TotalPoints":"0.00"},{"PlayerName":"Nate Stanley","PlayerId":"2564577","Pos":"QB","Team":"MIN","PassingYDS":"","PassingTD":"","PassingInt":"","RushingYDS":"","RushingTD":"","ReceivingRec":"","ReceivingYDS":"","ReceivingTD":"","RetTD":"","FumTD":"","2PT":"","Fum":"","FanPtsAgainst-pts":"16.42","TouchCarries":"","TouchReceptions":"","Touches":"","TargetsReceptions":"","Targets":"","ReceptionPercentage":"","RzTarget":"","RzTouch":"","RzG2G":"","Rank":111,"TotalPoints":"0.00"},{"PlayerName":"Drew Stanton","PlayerId":"2495748","Pos":"QB","Team":"FA","PassingYDS":"","PassingTD":"","PassingInt":"","RushingYDS":"","RushingTD":"","ReceivingRec":"","ReceivingYDS":"","ReceivingTD":"","RetTD":"","FumTD":"","2PT":"","Fum":"","FanPtsAgainst-pts":null,"TouchCarries":null,"TouchReceptions":null,"Touches":null,"TargetsReceptions":null,"Targets":null,"ReceptionPercentage":null,"RzTarget":null,"RzTouch":null,"RzG2G":null,"Rank":112,"TotalPoints":"0.00"},{"PlayerName":"Tommy Stevens","PlayerId":"2564697","Pos":"QB","Team":"FA","PassingYDS":"","PassingTD":"","PassingInt":"","RushingYDS":"","RushingTD":"","ReceivingRec":"","ReceivingYDS":"","ReceivingTD":"","RetTD":"","FumTD":"","2PT":"","Fum":"","FanPtsAgainst-pts":null,"TouchCarries":null,"TouchReceptions":null,"Touches":null,"TargetsReceptions":null,"Targets":null,"ReceptionPercentage":null,"RzTarget":null,"RzTouch":null,"RzG2G":null,"Rank":113,"TotalPoints":"0.00"},{"PlayerName":"Easton Stick","PlayerId":"2562745","Pos":"QB","Team":"LAC","PassingYDS":"","PassingTD":"","PassingInt":"","RushingYDS":"","RushingTD":"","ReceivingRec":"","ReceivingYDS":"","ReceivingTD":"","RetTD":"","FumTD":"","2PT":"","Fum":"","FanPtsAgainst-pts":"16.24","TouchCarries":"","TouchReceptions":"1","Touches":"1","TargetsReceptions":"1","Targets":"1","ReceptionPercentage":"100","RzTarget":"","RzTouch":"","RzG2G":"","Rank":114,"TotalPoints":"0.00"},{"PlayerName":"Jarrett Stidham","PlayerId":"2562746","Pos":"QB","Team":"NE","PassingYDS":"","PassingTD":"","PassingInt":"","RushingYDS":"","RushingTD":"","ReceivingRec":"","ReceivingYDS":"","ReceivingTD":"","RetTD":"","FumTD":"","2PT":"","Fum":"","FanPtsAgainst-pts":"15.48","TouchCarries":"","TouchReceptions":"","Touches":"","TargetsReceptions":"","Targets":"","ReceptionPercentage":"","RzTarget":"","RzTouch":"","RzG2G":"","Rank":115,"TotalPoints":"0.00"},{"PlayerName":"Nate Sudfeld","PlayerId":"2555427","Pos":"QB","Team":"SF","PassingYDS":"","PassingTD":"","PassingInt":"","RushingYDS":"","RushingTD":"","ReceivingRec":"","ReceivingYDS":"","ReceivingTD":"","RetTD":"","FumTD":"","2PT":"","Fum":"","FanPtsAgainst-pts":"14.65","TouchCarries":"","TouchReceptions":"","Touches":"","TargetsReceptions":"","Targets":"","ReceptionPercentage":"","RzTarget":"","RzTouch":"","RzG2G":"","Rank":116,"TotalPoints":"0.00"},{"PlayerName":"Clayton Thorson","PlayerId":"2562762","Pos":"QB","Team":"NYG","PassingYDS":"","PassingTD":"","PassingInt":"","RushingYDS":"","RushingTD":"","ReceivingRec":"","ReceivingYDS":"","ReceivingTD":"","RetTD":"","FumTD":"","2PT":"","Fum":"","FanPtsAgainst-pts":"22.13","TouchCarries":"","TouchReceptions":"","Touches":"","TargetsReceptions":"","Targets":"","ReceptionPercentage":"","RzTarget":"","RzTouch":"","RzG2G":"","Rank":117,"TotalPoints":"0.00"},{"PlayerName":"Kyle Trask","PlayerId":"2566571","Pos":"QB","Team":"TB","PassingYDS":"","PassingTD":"","PassingInt":"","RushingYDS":"","RushingTD":"","ReceivingRec":"","ReceivingYDS":"","ReceivingTD":"","RetTD":"","FumTD":"","2PT":"","Fum":"","FanPtsAgainst-pts":"15.29","TouchCarries":"","TouchReceptions":"","Touches":"","TargetsReceptions":"","Targets":"","ReceptionPercentage":"","RzTarget":"","RzTouch":"","RzG2G":"","Rank":118,"TotalPoints":"0.00"},{"PlayerName":"Deshaun Watson","PlayerId":"2558063","Pos":"QB","Team":"HOU","PassingYDS":"","PassingTD":"","PassingInt":"","RushingYDS":"","RushingTD":"","ReceivingRec":"","ReceivingYDS":"","ReceivingTD":"","RetTD":"","FumTD":"","2PT":"","Fum":"","FanPtsAgainst-pts":"16.38","TouchCarries":"","TouchReceptions":"","Touches":"","TargetsReceptions":"","Targets":"","ReceptionPercentage":"","RzTarget":"","RzTouch":"","RzG2G":"","Rank":119,"TotalPoints":"0.00"},{"PlayerName":"Chris Streveler","PlayerId":"2563458","Pos":"QB","Team":"BAL","PassingYDS":"36","PassingTD":"","PassingInt":"","RushingYDS":"6","RushingTD":"","ReceivingRec":"","ReceivingYDS":"","ReceivingTD":"","RetTD":"","FumTD":"","2PT":"","Fum":"1","FanPtsAgainst-pts":"16.26","TouchCarries":"3","TouchReceptions":"","Touches":"3","TargetsReceptions":"","Targets":"","ReceptionPercentage":"","RzTarget":"","RzTouch":"","RzG2G":"","Rank":120,"TotalPoints":"-0.09"},{"PlayerName":"Kurt Benkert","PlayerId":"2560974","Pos":"QB","Team":"GB","PassingYDS":"","PassingTD":"","PassingInt":"","RushingYDS":"-1","RushingTD":"","ReceivingRec":"","ReceivingYDS":"","ReceivingTD":"","RetTD":"","FumTD":"","2PT":"","Fum":"","FanPtsAgainst-pts":"17.47","TouchCarries":"2","TouchReceptions":"","Touches":"2","TargetsReceptions":"","Targets":"","ReceptionPercentage":"","RzTarget":"","RzTouch":"","RzG2G":"","Rank":121,"TotalPoints":"-0.10"},{"PlayerName":"Chase Daniel","PlayerId":"81284","Pos":"QB","Team":"LAC","PassingYDS":"","PassingTD":"","PassingInt":"","RushingYDS":"-2","RushingTD":"","ReceivingRec":"","ReceivingYDS":"","ReceivingTD":"","RetTD":"","FumTD":"","2PT":"","Fum":"","FanPtsAgainst-pts":"16.24","TouchCarries":"2","TouchReceptions":"","Touches":"2","TargetsReceptions":"","Targets":"","ReceptionPercentage":"","RzTarget":"","RzTouch":"","RzG2G":"","Rank":122,"TotalPoints":"-0.20"},{"PlayerName":"Davis Webb","PlayerId":"2557897","Pos":"QB","Team":"BUF","PassingYDS":"","PassingTD":"","PassingInt":"","RushingYDS":"-3","RushingTD":"","ReceivingRec":"","ReceivingYDS":"","ReceivingTD":"","RetTD":"","FumTD":"","2PT":"","Fum":"","FanPtsAgainst-pts":"18.22","TouchCarries":"2","TouchReceptions":"","Touches":"2","TargetsReceptions":"","Targets":"","ReceptionPercentage":"","RzTarget":"","RzTouch":"","RzG2G":"","Rank":123,"TotalPoints":"-0.30"},{"PlayerName":"Logan Woodside","PlayerId":"2560942","Pos":"QB","Team":"TEN","PassingYDS":"","PassingTD":"","PassingInt":"","RushingYDS":"-6","RushingTD":"","ReceivingRec":"","ReceivingYDS":"","ReceivingTD":"","RetTD":"","FumTD":"","2PT":"","Fum":"","FanPtsAgainst-pts":"16.31","TouchCarries":"6","TouchReceptions":"","Touches":"6","TargetsReceptions":"","Targets":"","ReceptionPercentage":"","RzTarget":"","RzTouch":"","RzG2G":"","Rank":124,"TotalPoints":"-0.60"},{"PlayerName":"Jacob Eason","PlayerId":"2564115","Pos":"QB","Team":"SEA","PassingYDS":"25","PassingTD":"","PassingInt":"1","RushingYDS":"","RushingTD":"","ReceivingRec":"","ReceivingYDS":"","ReceivingTD":"","RetTD":"","FumTD":"","2PT":"","Fum":"","FanPtsAgainst-pts":"15.63","TouchCarries":"","TouchReceptions":"","Touches":"","TargetsReceptions":"","Targets":"","ReceptionPercentage":"","RzTarget":"","RzTouch":"","RzG2G":"","Rank":125,"TotalPoints":"-1.00"},{"PlayerName":"Ryan Fitzpatrick","PlayerId":"2506581","Pos":"QB","Team":"WAS","PassingYDS":"13","PassingTD":"","PassingInt":"","RushingYDS":"2","RushingTD":"","ReceivingRec":"","ReceivingYDS":"","ReceivingTD":"","RetTD":"","FumTD":"","2PT":"","Fum":"1","FanPtsAgainst-pts":"16.39","TouchCarries":"1","TouchReceptions":"","Touches":"1","TargetsReceptions":"","Targets":"","ReceptionPercentage":"","RzTarget":"","RzTouch":"1","RzG2G":"","Rank":126,"TotalPoints":"-1.28"},{"PlayerName":"David Blough","PlayerId":"2563043","Pos":"QB","Team":"DET","PassingYDS":"","PassingTD":"","PassingInt":"","RushingYDS":"6","RushingTD":"","ReceivingRec":"","ReceivingYDS":"","ReceivingTD":"","RetTD":"","FumTD":"","2PT":"","Fum":"1","FanPtsAgainst-pts":"17.39","TouchCarries":"1","TouchReceptions":"","Touches":"1","TargetsReceptions":"","Targets":"","ReceptionPercentage":"","RzTarget":"","RzTouch":"","RzG2G":"","Rank":127,"TotalPoints":"-1.40"},{"PlayerName":"Feleipe Franks","PlayerId":"2566683","Pos":"QB","Team":"ATL","PassingYDS":"","PassingTD":"","PassingInt":"1","RushingYDS":"6","RushingTD":"","ReceivingRec":"","ReceivingYDS":"","ReceivingTD":"","RetTD":"","FumTD":"","2PT":"","Fum":"","FanPtsAgainst-pts":"15.38","TouchCarries":"3","TouchReceptions":"","Touches":"3","TargetsReceptions":"","Targets":"","ReceptionPercentage":"","RzTarget":"","RzTouch":"","RzG2G":"","Rank":128,"TotalPoints":"-1.40"},{"PlayerName":"John Wolford","PlayerId":"2561718","Pos":"QB","Team":"LA","PassingYDS":"5","PassingTD":"","PassingInt":"1","RushingYDS":"-1","RushingTD":"","ReceivingRec":"","ReceivingYDS":"","ReceivingTD":"","RetTD":"","FumTD":"","2PT":"","Fum":"","FanPtsAgainst-pts":"16.38","TouchCarries":"2","TouchReceptions":"","Touches":"2","TargetsReceptions":"","Targets":"","ReceptionPercentage":"","RzTarget":"","RzTouch":"","RzG2G":"","Rank":129,"TotalPoints":"-1.90"},{"PlayerName":"Josh Rosen","PlayerId":"2560858","Pos":"QB","Team":"ATL","PassingYDS":"19","PassingTD":"","PassingInt":"2","RushingYDS":"","RushingTD":"","ReceivingRec":"","ReceivingYDS":"","ReceivingTD":"","RetTD":"","FumTD":"","2PT":"","Fum":"","FanPtsAgainst-pts":"15.38","TouchCarries":"","TouchReceptions":"","Touches":"","TargetsReceptions":"","Targets":"","ReceptionPercentage":"","RzTarget":"","RzTouch":"","RzG2G":"","Rank":130,"TotalPoints":"-3.24"}]